spotify_aac_downloader/__init__.py
spotify_aac_downloader/__main__.py
spotify_aac_downloader/cli.py
spotify_aac_downloader/constants.py
spotify_aac_downloader/downloader.py
spotify_aac_downloader-1.5.4.dist-info/entry_points.txt
spotify_aac_downloader-1.5.4.dist-info/WHEEL
spotify_aac_downloader-1.5.4.dist-info/METADATA
spotify_aac_downloader-1.5.4.dist-info/RECORD
