Metadata-Version: 2.1
Name: spotify-aac-downloader
Version: 1.5.4
Summary: Download songs/albums/playlists directly from Spotify in AAC
Author: glomatico
Requires-Python: >=3.7
Requires-Dist: click
Requires-Dist: pybase62
Requires-Dist: pywidevine
Requires-Dist: pyyaml
Requires-Dist: yt-dlp
Project-URL: repository, https://github.com/glomatico/spotify-aac-downloader
